pytorch_ggd/GGD.py
pytorch_ggd-0.0.3.dist-info/METADATA
pytorch_ggd-0.0.3.dist-info/WHEEL
pytorch_ggd-0.0.3.dist-info/top_level.txt
pytorch_ggd-0.0.3.dist-info/RECORD
