Metadata-Version: 2.1
Name: pytorch_ggd
Version: 0.0.3
Summary: Generalized Gaussian distribution in pytorch 
Author-email: Dan Jacobellis <danjacobellis@utexas.edu>
Classifier: Programming Language :: Python :: 3
Classifier: Operating System :: OS Independent
Requires-Python: >=3.6
Requires-Dist: torch
